notemovie/__init__.py
notemovie/database/__init__.py
notemovie/database/core.py
notemovie/database/core_redis.py
notemovie/database/job.py
notemovie/library/__init__.py
notemovie/library/core.py
notemovie/library/core1.py
notemovie/library/get_magnet.py
notemovie/magnet/__init__.py
notemovie/magnet/core.py
notemovie/magnet/crawler.py
notemovie/magnet/magnet_to_torrent_aria2c.py
notemovie/magnet/parse_torrent.py
notemovie/magnet/tracker_list.py
notemovie/magnet/utils.py
notemovie/utils/__init__.py
notemovie/utils/core.py
notemovie-0.0.3.dist-info/METADATA
notemovie-0.0.3.dist-info/WHEEL
notemovie-0.0.3.dist-info/top_level.txt
notemovie-0.0.3.dist-info/RECORD
